sphinx_markdown_parser/__init__.py
sphinx_markdown_parser/commonmark_parser.py
sphinx_markdown_parser/depth.py
sphinx_markdown_parser/markdown_parser.py
sphinx_markdown_parser/parser.py
sphinx_markdown_parser/scripts.py
sphinx_markdown_parser/states.py
sphinx_markdown_parser/transform.py
sphinx_markdown_parser-0.2.4.dist-info/LICENSE
sphinx_markdown_parser-0.2.4.dist-info/METADATA
sphinx_markdown_parser-0.2.4.dist-info/WHEEL
sphinx_markdown_parser-0.2.4.dist-info/entry_points.txt
sphinx_markdown_parser-0.2.4.dist-info/top_level.txt
sphinx_markdown_parser-0.2.4.dist-info/RECORD
