Metadata-Version: 2.1
Name: sphinx_markdown_parser
Version: 0.2.4
Summary: A docutils-compatibility bridge to markdown, enabling you to write markdown with support for tables inside of docutils & sphinx projects.
Home-page: https://github.com/codejamninja/sphinx-markdown-parser
Author: Jam Risser
Author-email: jam@codejam.ninja
License: MIT
Keywords: sphinx docs documentation markdown
Platform: UNKNOWN
Classifier: Intended Audience :: Developers
Classifier: Topic :: Utilities
Classifier: License :: OSI Approved :: MIT License
Classifier: Programming Language :: Python :: 3
Classifier: Programming Language :: Python :: 3.5
Classifier: Programming Language :: Python :: 3.6
Classifier: Programming Language :: Python :: 3.7
